telegramApi/__init__.py
telegramApi/telegramApi.py
telegramApi-1.5.dist-info/LICENSE
telegramApi-1.5.dist-info/METADATA
telegramApi-1.5.dist-info/WHEEL
telegramApi-1.5.dist-info/top_level.txt
telegramApi-1.5.dist-info/RECORD
